tasks.py
pelican/plugins/minify/__init__.py
pelican/plugins/minify/minify.py
pelican_minify-2.0.0.dist-info/METADATA
pelican_minify-2.0.0.dist-info/WHEEL
pelican_minify-2.0.0.dist-info/licenses/LICENSE
pelican_minify-2.0.0.dist-info/RECORD
