Metadata-Version: 2.1
Name: pelican-minify
Version: 2.0.0
Summary: Pelican plugin to minify HTML, CSS and Javascript
Project-URL: Homepage, https://github.com/pelican-plugins/minify
Project-URL: Issue Tracker, https://github.com/pelican-plugins/minify/issues
Project-URL: Funding, https://donate.getpelican.com/
Author-email: Alexander Herrmann <106409+dArignac@users.noreply.github.com>, Justin Mayer <entroP@gmail.com>, Ysard <ysard@users.noreply.github.com>
License: MIT
License-File: LICENSE
Keywords: css,html,javascript,minification,minify,pelican,plugin
Classifier: Development Status :: 5 - Production/Stable
Classifier: Environment :: Console
Classifier: Framework :: Pelican
Classifier: Framework :: Pelican :: Plugins
Classifier: Intended Audience :: End Users/Desktop
Classifier: License :: OSI Approved :: MIT License
Classifier: Operating System :: OS Independent
Classifier: Programming Language :: Python :: 3
Classifier: Programming Language :: Python :: 3.8
Classifier: Programming Language :: Python :: 3.9
Classifier: Programming Language :: Python :: 3.10
Classifier: Programming Language :: Python :: 3.11
Classifier: Topic :: Internet :: WWW/HTTP
Classifier: Topic :: Software Development :: Libraries :: Python Modules
Requires-Python: <4.0,>=3.8.1
Requires-Dist: minify-html>=0.10.8
Requires-Dist: pelican>=4.5
Provides-Extra: markdown
Requires-Dist: markdown>=3.4; extra == 'markdown'
